baidu_trans_cli/__init__.py
baidu_trans_cli-0.2.2.dist-info/METADATA
baidu_trans_cli-0.2.2.dist-info/RECORD
baidu_trans_cli-0.2.2.dist-info/WHEEL
baidu_trans_cli-0.2.2.dist-info/entry_points.txt
baidu_trans_cli-0.2.2.dist-info/top_level.txt
