Metadata-Version: 2.1
Name: baidu-trans-cli
Version: 0.2.2
Summary: use baidu translation api in terminal
Home-page: https://gitee.com/gin9/baidu-trans-cli/tree/master/
Author: gin9
Author-email: kuangcp@aliyun.com
License: MIT License
Keywords: translation
Platform: any
Classifier: Development Status :: 5 - Production/Stable
Classifier: Intended Audience :: Developers
Classifier: Natural Language :: Chinese (Simplified)
Classifier: Natural Language :: English
Classifier: Topic :: Utilities
Classifier: Topic :: Terminals
Classifier: Topic :: System :: Distributed Computing
Classifier: License :: OSI Approved :: MIT License
Classifier: Programming Language :: Python :: 3
Classifier: Programming Language :: Python :: 3.3
Classifier: Programming Language :: Python :: 3.4
Classifier: Programming Language :: Python :: 3.5
Classifier: Programming Language :: Python :: 3.6
Requires-Dist: fire (>=0.1.3)
Requires-Dist: requests (>=2.19.1)
Requires-Dist: urllib3 (>=1.23)
Requires-Dist: pyperclip (>=1.7.0)
